ISCNSNAKE/ISCNParser.py
ISCNSNAKE/ISCN_storage.h5
ISCNSNAKE/__init__.py
ISCNSNAKE/quick_SNAKE.py
ISCNSNAKE/run_SNAKE.py
ISCNSNAKE/testSNAKE.py
ISCNSNAKE/tests.py
ISCNSNAKE-2.3.2.dist-info/METADATA
ISCNSNAKE-2.3.2.dist-info/RECORD
ISCNSNAKE-2.3.2.dist-info/WHEEL
ISCNSNAKE-2.3.2.dist-info/top_level.txt
