Metadata-Version: 2.1
Name: ISCNSNAKE
Version: 2.3.2
Summary: A parser for ISCN data.
Home-page: https://gitlab.com/connordenomy/ISCN-SNAKE
Author: Connor Denomy
Author-email: connordenomy@gmail.com
License: MIT
Platform: UNKNOWN
Classifier: License :: OSI Approved :: MIT License
Classifier: Programming Language :: Python
Classifier: Programming Language :: Python :: 3
Classifier: Programming Language :: Python :: 3.6
Classifier: Programming Language :: Python :: Implementation :: CPython
Classifier: Programming Language :: Python :: Implementation :: PyPy
Requires-Python: >=3.6.0
Requires-Dist: pandas
Requires-Dist: numpy
